Metadata-Version: 1.1
Name: pybel-orca
Version: 0.2
Summary: ORCA input file writer
Home-page: https://github.com/mohebifar/pybel-orca
Author: Mohamad Mohebifar
Author-email: mmohebifar@mun.ca
License: UNKNOWN
Download-URL: https://github.com/mohebifar/pybel-orca/tarball/0.1
Keywords: pybel-orca,rowley
Platform: UNKNOWN
